{
  "title": "2010 Golf 11.JPG",
  "description": "\"Cinderella story ... out of nowwhere ... it's in the hole!\" \n- Carl Spackler",
  "imageViews": "82",
  "creationTime": {
    "timestamp": "1274045093",
    "formatted": "May 16, 2010, 9:24:53 PM UTC"
  },
  "photoTakenTime": {
    "timestamp": "1273845428",
    "formatted": "May 14, 2010, 1:57:08 PM UTC"
  },
  "geoData": {
    "latitude": 0.0,
    "longitude": 0.0,
    "altitude": 0.0,
    "latitudeSpan": 0.0,
    "longitudeSpan": 0.0
  },
  "url": "https://photos.google.com/photo/AF1QipPMdAR2s7d44-xXnf3SZY9BOtLxDSRsegxT-M18"
}