{
  "title": "2010 Golf 25.JPG",
  "description": "Tyler Bitancurt, WVU Football placekicker",
  "imageViews": "162",
  "creationTime": {
    "timestamp": "1274095898",
    "formatted": "May 17, 2010, 11:31:38 AM UTC"
  },
  "photoTakenTime": {
    "timestamp": "1273860895",
    "formatted": "May 14, 2010, 6:14:55 PM UTC"
  },
  "geoData": {
    "latitude": 0.0,
    "longitude": 0.0,
    "altitude": 0.0,
    "latitudeSpan": 0.0,
    "longitudeSpan": 0.0
  },
  "url": "https://photos.google.com/photo/AF1QipNagFQS0S4tjyQyzAU6VqEWyRuvrnYSwCBaZY9V"
}