{
  "title": "CVFB Donation - Rutgers Gamewatch.jpg",
  "description": "",
  "imageViews": "138",
  "creationTime": {
    "timestamp": "1260115599",
    "formatted": "Dec 6, 2009, 4:06:39 PM UTC"
  },
  "photoTakenTime": {
    "timestamp": "1259989115",
    "formatted": "Dec 5, 2009, 4:58:35 AM UTC"
  },
  "geoData": {
    "latitude": 0.0,
    "longitude": 0.0,
    "altitude": 0.0,
    "latitudeSpan": 0.0,
    "longitudeSpan": 0.0
  },
  "url": "https://photos.google.com/photo/AF1QipMP087MLzFaHxKAM2qbo7cv8DOPPzECj5dYlZ5D"
}